async_armor
