Metadata-Version: 1.1
Name: async-armor
Version: 0.0.2
Summary: Graceful drop-in replacement for asyncio.shield
Home-page: https://github.com/wikibusiness/async_armor
Author: wikibusiness
Author-email: osf@wikibusiness.org
License: UNKNOWN
Keywords: asyncio,asyncio.shield,graceful
Platform: UNKNOWN
Classifier: Development Status :: 4 - Beta
Classifier: Intended Audience :: Developers
Classifier: License :: OSI Approved :: MIT License
Classifier: Programming Language :: Python
Classifier: Programming Language :: Python :: 3
Classifier: Programming Language :: Python :: 3.3
Classifier: Programming Language :: Python :: 3.4
Classifier: Programming Language :: Python :: 3.5
Classifier: Programming Language :: Python :: 3.6
